{"1":{"class_name":"Adult Dance Class","class_description":""},"2":{"class_name":"Pre L1 Ballet","class_description":""},"4":{"class_name":"Pre L1 Tap","class_description":""},"5":{"class_name":"L1 Jazz Group A","class_description":""},"6":{"class_name":"L1 Jazz Group B","class_description":""},"32":{"class_name":"L2 Jazz Group A","class_description":""},"7":{"class_name":"L1 Tap","class_description":""},"8":{"class_name":"L3 Jazz Group C","class_description":""},"9":{"class_name":"Private Lessons","class_description":""},"10":{"class_name":"L2 Tap","class_description":""},"33":{"class_name":"L2 Jazz Group B","class_description":""}}